[
  {
    "title": "Juegos y Actividades presenciales",
    "url": "http://u.uma.es/clY"
  },
  {
    "title": "OSU!",
    "date": "18:00 - Viernes 8 de abril",
    "url": "http://u.uma.es/cl0",
    "ubicacion": "Online"
  },
  {
    "title": "League Of Legends",
    "date": "12:00 - Sábado 9 de abril",
    "url": "http://u.uma.es/cjq",
    "ubicacion": "Online"
  },
  {
    "title": "Rocket League",
    "date": "12:00 - Domingo 10 de abril",
    "url": "http://u.uma.es/cly",
    "ubicacion": "Online"
  }
]
